i3_swap_focus.py
i3_swap_focus-0.4.7.dist-info/licenses/LICENSE
i3_swap_focus-0.4.7.dist-info/METADATA
i3_swap_focus-0.4.7.dist-info/WHEEL
i3_swap_focus-0.4.7.dist-info/entry_points.txt
i3_swap_focus-0.4.7.dist-info/top_level.txt
i3_swap_focus-0.4.7.dist-info/RECORD
