Metadata-Version: 2.4
Name: i3-swap-focus
Version: 0.4.7
Summary: i3/sway script to toggle between last windows
Author-email: Olivier Le Moal <mail@olivierlemoal.fr>
License: MIT
Project-URL: Homepage, https://codeberg.org/olivierlm/i3-swap-focus
Requires-Python: >=3.7
License-File: LICENSE
Requires-Dist: i3ipc
Dynamic: license-file
